{
	"pins": [
		{
			"title": "matcha",
			"class": "_active",
			"commentCount": 39,
			"shareCount": 40,
			"saveCount": 20,
			"creator": " John Smith",
			"createImg": "a-4",
			"followingCount": "3k",
			"pages": [
				{
					"src" : "matcha-1",
					"class": "_active"
				},
				{
					"src" : "matcha-2",
					"class": ""
				},
				{
					"src" : "matcha-3",
					"class": ""
				},
				{
					"src" : "matcha-4",
					"class": ""
				}
			]
		},
		{
			"title": "chicken",
			"class": "",
			"commentCount": 39,
			"shareCount": 40,
			"saveCount": 20,
			"creator": " John Smith",
			"createImg": "a-4",
			"followingCount": "3k",
			"pages": [
				{
					"src" : "chicken-1",
					"class": ""
				},
				{
					"src" : "chicken-2",
					"class": ""
				},
				{
					"src" : "chicken-3",
					"class": ""
				},
				{
					"src" : "chicken-4",
					"class": ""
				}
			]
		}
	],
		"thelastpin": [
		{
			"title": "matcha",
			"class": "_do-not-play",
			"commentCount": 39,
			"shareCount": 40,
			"saveCount": 20,
			"creator": " John Smith",
			"createImg": "a-4",
			"followingCount": "3k",
			"pages": [
				{
					"src" : "matcha-1",
					"class": "_active"
				},
				{
					"src" : "matcha-2",
					"class": ""
				},
				{
					"src" : "matcha-3",
					"class": ""
				},
				{
					"src" : "matcha-4",
					"class": ""
				}
			]
		}
	]
}